hello/__init__.py
hello/main.py
hello_world_uzb-0.0.1.dist-info/METADATA
hello_world_uzb-0.0.1.dist-info/WHEEL
hello_world_uzb-0.0.1.dist-info/top_level.txt
hello_world_uzb-0.0.1.dist-info/RECORD
