Metadata-Version: 2.1
Name: hello_world_uzb
Version: 0.0.1
Summary: siz bunda hello world so'zini chiqarasiz
Author: salohiddin
Author-email: salohiddinsalohiddin123@gmail.com
Classifier: Programming Language :: Python :: 3
Classifier: License :: OSI Approved :: MIT License
Classifier: Operating System :: OS Independent
